CHANGELOG.md
LICENSE.txt
django_sb_simple_migrations/__init__.py
django_sb_simple_migrations/admin.py
django_sb_simple_migrations/apps.py
django_sb_simple_migrations/conf.py
django_sb_simple_migrations/management/__init__.py
django_sb_simple_migrations/management/commands/__init__.py
django_sb_simple_migrations/management/commands/makemigrations.py
django_sb_simple_migrations/management/commands/migrate.py
django_sb_simple_migrations/migrations/__init__.py
django_sb_simple_migrations/models.py
django_sb_simple_migrations/tests.py
django_sb_simple_migrations/version.py
django_sb_simple_migrations/views.py
django_sb_simple_migrations-0.9.0.dist-info/LICENSE.txt
django_sb_simple_migrations-0.9.0.dist-info/METADATA
django_sb_simple_migrations-0.9.0.dist-info/WHEEL
django_sb_simple_migrations-0.9.0.dist-info/RECORD
