Metadata-Version: 2.1
Name: django-sb-simple-migrations
Version: 0.9.0
Summary: Django migrations without unnecesary change alert triggers.
Home-page: https://gitlab.com/softbutterfly/open-source/django-sb-simple-migrations
License: MIT
Keywords: Softbutterfly,Django,Migrations
Author: SoftButterfly Development Team
Author-email: dev@softbutterfly.io
Requires-Python: >=3.9.0,<4.0.0
Classifier: Development Status :: 5 - Production/Stable
Classifier: Environment :: Web Environment
Classifier: Framework :: Django :: 4.2
Classifier: Framework :: Django :: 5.0
Classifier: Framework :: Django :: 5.1
Classifier: Intended Audience :: Developers
Classifier: License :: OSI Approved :: MIT License
Classifier: Natural Language :: English
Classifier: Programming Language :: Python :: 3
Classifier: Programming Language :: Python :: 3.9
Classifier: Programming Language :: Python :: 3.10
Classifier: Programming Language :: Python :: 3.11
Classifier: Programming Language :: Python :: 3.12
Classifier: Topic :: Software Development :: Libraries :: Python Modules
Requires-Dist: Django (<6.0.0)
Project-URL: Bug Tracker, https://github.com/softbutterfly/django-sb-simple-migrations/issues
Project-URL: Documentation, https://gitlab.com/softbutterfly/open-source/django-sb-simple-migrations/-/wikis
Project-URL: Download, https://github.com/softbutterfly/django-sb-simple-migrations/archive/v0.9.0.tar.gz
Project-URL: Repository, https://gitlab.com/softbutterfly/open-source/django-sb-simple-migrations
